outbreaker/__init__.py
outbreaker/__main__.py
outbreaker/classes.py
outbreaker/utils.py
outbreaker-1.0.5.dist-info/LICENSE
outbreaker-1.0.5.dist-info/METADATA
outbreaker-1.0.5.dist-info/WHEEL
outbreaker-1.0.5.dist-info/entry_points.txt
outbreaker-1.0.5.dist-info/top_level.txt
outbreaker-1.0.5.dist-info/RECORD
