Metadata-Version: 2.1
Name: outbreaker
Version: 1.0.5
Summary: Explore WHO Disease Outbreak News
Home-page: https://github.com/mattravenhall/outbreaker
Author: Matt Ravenhall
Author-email: matt.ravenhall@gmail.com
License: UNKNOWN
Platform: UNKNOWN
Classifier: Development Status :: 5 - Production/Stable
Classifier: Environment :: Console
Classifier: Intended Audience :: Science/Research
Classifier: License :: OSI Approved :: Python Software Foundation License
Classifier: Operating System :: MacOS :: MacOS X
Classifier: Operating System :: Microsoft :: Windows
Classifier: Operating System :: POSIX
Classifier: Programming Language :: Python
Classifier: Topic :: Scientific/Engineering :: Bio-Informatics
Requires-Python: >=3.7
Requires-Dist: beautifulsoup4 (>=4.6.0)
Requires-Dist: requests
Requires-Dist: lxml
